crfsuite/__init__.py
crfsuite/_compat.py
crfsuite/_native.py
crfsuite/_native__ffi.py
crfsuite/_native__lib.so
crfsuite/exceptions.py
crfsuite/utils.py
crfsuite-0.3.1.dist-info/LICENSE
crfsuite-0.3.1.dist-info/METADATA
crfsuite-0.3.1.dist-info/WHEEL
crfsuite-0.3.1.dist-info/top_level.txt
crfsuite-0.3.1.dist-info/RECORD
