Metadata-Version: 2.1
Name: crfsuite
Version: 0.3.1
Summary: Python binding for crfsuite
Home-page: https://github.com/bosondata/crfsuite-rs
License: UNKNOWN
Platform: any
